hetzner_speed_test/__main__.py
hetzner_speedtest-0.1.0.dist-info/METADATA
hetzner_speedtest-0.1.0.dist-info/WHEEL
hetzner_speedtest-0.1.0.dist-info/entry_points.txt
hetzner_speedtest-0.1.0.dist-info/RECORD
